MANIFEST.in
README.rst
VERSION
requirements.txt
setup.cfg
setup.py
patton_server/__init__.py
patton_server/command_line.py
patton_server/exceptions.py
patton_server.egg-info/PKG-INFO
patton_server.egg-info/SOURCES.txt
patton_server.egg-info/dependency_links.txt
patton_server.egg-info/entry_points.txt
patton_server.egg-info/requires.txt
patton_server.egg-info/top_level.txt
patton_server/dal/__init__.py
patton_server/dal/create_tables.sql
patton_server/dal/database.py
patton_server/dal/loader.py
patton_server/dal/models.py
patton_server/dal/updater.py
patton_server/dal/common/__init__.py
patton_server/dal/common/fields.py
patton_server/dal/product/__init__.py
patton_server/dal/product/fields.py
patton_server/dal/product/models.py
patton_server/dal/vulnerability/__init__.py
patton_server/dal/vulnerability/fields.py
patton_server/dal/vulnerability/models.py
patton_server/service/__init__.py
patton_server/service/end_points_api_v1.py
patton_server/service/end_points_home.py
patton_server/service/make_web_app.py
patton_server/service/banners_managers/__init__.py
patton_server/service/banners_managers/banners_managers_v2.py
patton_server/service/cpes_managers/__init__.py
patton_server/service/cpes_managers/cpe_managers_v1.py
patton_server/service/cpes_managers/cpe_managers_v2.py
patton_server/service/input_sources/__init__.py
patton_server/service/input_sources/alpine.py
patton_server/service/input_sources/dpkg.py
patton_server/service/input_sources/maven.py
patton_server/service/input_sources/simple.py