Metadata-Version: 1.1
Name: patton-server
Version: 1.1.0
Summary: The vulnerability knowledge store
Home-page: https://github.com/bbva/patton-server
Author: BBVA Labs
Author-email: UNKNOWN
License: MIT
Platform: UNKNOWN
Classifier: Environment :: Console
Classifier: Intended Audience :: System Administrators
Classifier: Intended Audience :: Other Audience
Classifier: License :: OSI Approved :: BSD License
Classifier: Operating System :: MacOS
Classifier: Operating System :: Microsoft :: Windows
Classifier: Operating System :: POSIX
Classifier: Programming Language :: Python :: 3
